kriptik/__init__.py
kriptik/kriptik.py
Kriptik-0.0.5.dist-info/METADATA
Kriptik-0.0.5.dist-info/WHEEL
Kriptik-0.0.5.dist-info/top_level.txt
Kriptik-0.0.5.dist-info/RECORD
